check_zpools/__init__.py
check_zpools/__init__conf__.py
check_zpools/__main__.py
check_zpools/alert_state.py
check_zpools/alerting.py
check_zpools/alias_manager.py
check_zpools/behaviors.py
check_zpools/cli.py
check_zpools/cli_email_handlers.py
check_zpools/cli_errors.py
check_zpools/cli_traceback.py
check_zpools/config.py
check_zpools/config_deploy.py
check_zpools/config_show.py
check_zpools/daemon.py
check_zpools/defaultconfig.toml
check_zpools/formatters.py
check_zpools/logging_setup.py
check_zpools/mail.py
check_zpools/models.py
check_zpools/monitor.py
check_zpools/py.typed
check_zpools/service_install.py
check_zpools/zfs_client.py
check_zpools/zfs_parser.py
check_zpools/cli_commands/__init__.py
check_zpools/cli_commands/commands/__init__.py
check_zpools/cli_commands/commands/alias_create.py
check_zpools/cli_commands/commands/alias_delete.py
check_zpools/cli_commands/commands/check.py
check_zpools/cli_commands/commands/config_deploy.py
check_zpools/cli_commands/commands/config_show.py
check_zpools/cli_commands/commands/daemon.py
check_zpools/cli_commands/commands/send_email.py
check_zpools/cli_commands/commands/send_notification.py
check_zpools/cli_commands/commands/service_install.py
check_zpools/cli_commands/commands/service_status.py
check_zpools/cli_commands/commands/service_uninstall.py
check_zpools-3.7.1.dist-info/METADATA
check_zpools-3.7.1.dist-info/WHEEL
check_zpools-3.7.1.dist-info/entry_points.txt
check_zpools-3.7.1.dist-info/licenses/LICENSE
check_zpools-3.7.1.dist-info/RECORD
