Metadata-Version: 2.4
Name: check_zpools
Version: 3.7.1
Summary: Zpool Monitoring Daemon
Project-URL: Homepage, https://github.com/bitranox/check_zpools
Project-URL: Repository, https://github.com/bitranox/check_zpools.git
Project-URL: Issues, https://github.com/bitranox/check_zpools/issues
Author-email: bitranox <bitranox@gmail.com>
License: MIT
License-File: LICENSE
Keywords: cli,daemon,monitoring,zpool
Classifier: Environment :: Console
Classifier: License :: OSI Approved :: MIT License
Classifier: Operating System :: OS Independent
Classifier: Programming Language :: Python :: 3
Classifier: Programming Language :: Python :: 3 :: Only
Classifier: Typing :: Typed
Requires-Python: >=3.13
Requires-Dist: btx-lib-mail>=1.3.0
Requires-Dist: lib-cli-exit-tools>=2.2.4
Requires-Dist: lib-layered-config>=5.4.0
Requires-Dist: lib-log-rich>=6.3.1
Requires-Dist: psutil>=7.2.2
Requires-Dist: pydantic>=2.12.5
Requires-Dist: python-dateutil>=2.9.0.post0
Requires-Dist: rich-click>=1.9.7
Provides-Extra: dev
Requires-Dist: bandit>=1.9.3; extra == 'dev'
Requires-Dist: build>=1.4.0; extra == 'dev'
Requires-Dist: codecov-cli>=11.2.6; extra == 'dev'
Requires-Dist: import-linter>=2.9; extra == 'dev'
Requires-Dist: pip-audit>=2.10.0; extra == 'dev'
Requires-Dist: pyright[nodejs]>=1.1.408; extra == 'dev'
Requires-Dist: pytest-cov>=7.0.0; extra == 'dev'
Requires-Dist: pytest>=9.0.2; extra == 'dev'
Requires-Dist: rtoml>=0.13.0; extra == 'dev'
Requires-Dist: ruff>=0.14.14; extra == 'dev'
Requires-Dist: textual>=7.5.0; extra == 'dev'
Requires-Dist: twine>=6.2.0; extra == 'dev'
